wbddh/__init__.py
wbddh/ddh_exceptions.py
wbddh/exceptions.py
wbddh/request_manager.py
wbddh/session.py
wbddh/session_manager.py
wbddh/test.py
wbddh/utils.py
wbddh-0.1.13.dist-info/METADATA
wbddh-0.1.13.dist-info/WHEEL
wbddh-0.1.13.dist-info/top_level.txt
wbddh-0.1.13.dist-info/RECORD
