Metadata-Version: 2.1
Name: wbddh
Version: 0.1.13
Summary: Python wrapper for DDH Open API
Home-page: https://github.com/WB-DECIS/WBDDH
Author: DECID
Requires-Dist: requests
Provides-Extra: curation
Requires-Dist: msal ; extra == 'curation'
Requires-Dist: pyyaml ; extra == 'curation'
Provides-Extra: internal
Requires-Dist: msal ; extra == 'internal'
Requires-Dist: pyyaml ; extra == 'internal'
